mcc/__init__.py
mcc/cashflow_generation.py
mcc/cashflows.py
mcc/contracts.py
mcc/model.py
mcc/observables.py
mcc/reusable_contracts.py
mcc/pricing_models/__init__.py
mcc/pricing_models/black_scholes.py
mcc/pricing_models/financial.py
mcc/pricing_models/ho_lee.py
mcc/pricing_models/stochastic_processes.py
monte_carlo_contracts-0.10.0.data/data/HISTORY.md
monte_carlo_contracts-0.10.0.data/data/LICENSE
monte_carlo_contracts-0.10.0.dist-info/LICENSE
monte_carlo_contracts-0.10.0.dist-info/METADATA
monte_carlo_contracts-0.10.0.dist-info/WHEEL
monte_carlo_contracts-0.10.0.dist-info/top_level.txt
monte_carlo_contracts-0.10.0.dist-info/zip-safe
monte_carlo_contracts-0.10.0.dist-info/RECORD
