Metadata-Version: 2.1
Name: monte-carlo-contracts
Version: 0.10.0
Summary: Composable financial contracts with Monte Carlo valuation 
Home-page: https://github.com/luphord/monte-carlo-contracts
Author: luphord
Author-email: luphord@protonmail.com
License: MIT license
Keywords: composable financial contracts Monte Carlo method
Classifier: Development Status :: 3 - Alpha
Classifier: Intended Audience :: Developers
Classifier: License :: OSI Approved :: MIT License
Classifier: Natural Language :: English
Classifier: Programming Language :: Python :: 3
Classifier: Programming Language :: Python :: 3.8
Classifier: Programming Language :: Python :: 3.9
Classifier: Programming Language :: Python :: 3.10
Classifier: Programming Language :: Python :: 3.11
Requires-Python: >=3.8
License-File: LICENSE
Requires-Dist: numpy (>=1.24)
Requires-Dist: pandas (>=1.5)
